fosvis/__init__.py
fosvis/diagram_and_legend.py
fosvis/fosvis.py
fosvis/links.py
fosvis/orf.py
fosvis/protein_domains.py
fosvis/running_visualize_fosmids.py
fosvis/seq_util.py
test/__init__.py
test/test_diagram_and_legend.py
test/test_fosvis.py
test/test_links.py
test/test_orf.py
test/test_protein_domains.py
test/test_seq_util.py
fosvis-1.0.0.dist-info/METADATA
fosvis-1.0.0.dist-info/WHEEL
fosvis-1.0.0.dist-info/top_level.txt
fosvis-1.0.0.dist-info/RECORD
