Metadata-Version: 2.1
Name: fosvis
Version: 1.0.0
Summary: A tool for visualizing fosmid DNA sequences.
Home-page: UNKNOWN
Author: Tylo Roberts
Author-email: tylojroberts@gmail.com
License: MIT
Platform: UNKNOWN
Requires-Dist: biopython
Requires-Dist: pandas
Requires-Dist: numpy
Requires-Dist: matplotlib
Requires-Dist: seaborn
Requires-Dist: tqdm
